AUTHORS.rst
CONTRIBUTING.rst
HISTORY.rst
LICENSE
MANIFEST.in
README.rst
setup.cfg
setup.py
docs/Makefile
docs/authors.rst
docs/conf.py
docs/contributing.rst
docs/history.rst
docs/index.rst
docs/installation.rst
docs/make.bat
docs/readme.rst
docs/usage.rst
magic_lightning_remote/__init__.py
magic_lightning_remote/magic_lightning_remote.py
magic_lightning_remote.egg-info/PKG-INFO
magic_lightning_remote.egg-info/SOURCES.txt
magic_lightning_remote.egg-info/dependency_links.txt
magic_lightning_remote.egg-info/not-zip-safe
magic_lightning_remote.egg-info/requires.txt
magic_lightning_remote.egg-info/top_level.txt
tests/__init__.py
tests/test_magic_lightning_remote.py