Metadata-Version: 1.1
Name: magic-lightning-remote
Version: 0.1.0
Summary: Web controller for the magic lightning irda lamplight (acheap rgb irda controlled lightbulb)
Home-page: https://github.com/XayOn/magic_lightning_remote
Author: David Francos Cuartero
Author-email: me@davidfrancos.net
License: BSD
Keywords: magic_lightning_remote
Platform: UNKNOWN
Classifier: Development Status :: 2 - Pre-Alpha
Classifier: Intended Audience :: Developers
Classifier: License :: OSI Approved :: BSD License
Classifier: Natural Language :: English
Classifier: Programming Language :: Python :: 2
Classifier: Programming Language :: Python :: 2.6
Classifier: Programming Language :: Python :: 2.7
Classifier: Programming Language :: Python :: 3
Classifier: Programming Language :: Python :: 3.3
Classifier: Programming Language :: Python :: 3.4
